byhacker_speech_to_text/__init__.py
byhacker_speech_to_text/main.py
byhacker_speech_to_text/speech_to_text.py
byhacker_speech_to_text-0.1.2.dist-info/licenses/LICENSE
byhacker_speech_to_text-0.1.2.dist-info/METADATA
byhacker_speech_to_text-0.1.2.dist-info/WHEEL
byhacker_speech_to_text-0.1.2.dist-info/top_level.txt
byhacker_speech_to_text-0.1.2.dist-info/RECORD
