Metadata-Version: 2.4
Name: byhacker_speech_to_text
Version: 0.1.2
Summary: A speech-to-text package using Selenium browser listener
Home-page: https://github.com/romil4648/byhacker_speech_to_text
Author: Romil Leuva
Author-email: example@example.com
License-File: LICENSE
Requires-Dist: selenium
Dynamic: author
Dynamic: author-email
Dynamic: home-page
Dynamic: license-file
Dynamic: requires-dist
Dynamic: summary
